{
  "global": {
    "total_market_cap": 2341620119701.085,
    "total_volume_24h": 116854910099.80292,
    "market_cap_change_24h": -3.497274690733923,
    "btc_dominance": 56.661555949239975,
    "eth_dominance": 9.945488988477724,
    "active_cryptocurrencies": 18936,
    "fear_greed_index": 11,
    "fear_greed_classification": "Extreme Fear",
    "alt_season_index": 44,
    "total_open_interest": 8848008241.756523,
    "total_liquidations_24h": 0.0,
    "btc_price": 66480.62417391,
    "btc_change_24h": 0.0,
    "btc_funding_rate": -1.378e-05,
    "btc_open_interest": 5403329403.22996,
    "eth_price": 1930.20465116,
    "eth_change_24h": 0.0,
    "eth_funding_rate": -0.00012343,
    "eth_open_interest": 3444678838.5265636,
    "timestamp": 1770825307,
    "sources": [
      "coingecko",
      "alternative.me",
      "binance"
    ]
  },
  "BTC": {
    "price": {
      "ticker": "BTC",
      "price_usd": 66471.3,
      "price_change_24h": -4.146,
      "price_change_1h": 0.0,
      "price_change_7d": 0.0,
      "high_24h": 69957.9,
      "low_24h": 65718.5,
      "volume_24h": 15595896954.19,
      "volume_change_24h": 0.0,
      "market_cap": 1325302383184.0,
      "market_cap_rank": 1,
      "circulating_supply": 19987678.0,
      "total_supply": 19987678.0,
      "ath": 126080.0,
      "ath_change_percentage": -47.31898,
      "timestamp": 1770825312,
      "source": "binance+coingecko"
    },
    "timestamp": 1770825312,
    "derivatives": {
      "ticker": "BTC",
      "funding_rate": -1.378e-05,
      "funding_rate_24h_ago": -8.417e-05,
      "funding_rate_change_24h": 7.039000000000001e-05,
      "next_funding_time": 1770825600,
      "open_interest_usd": 5401327701.612583,
      "open_interest_base": 81271.162,
      "open_interest_change_24h": 0.0,
      "liquidations_24h_long": 0,
      "liquidations_24h_short": 0,
      "liquidations_24h_total": 0,
      "long_short_ratio": 2.0102,
      "mark_price": 66460.5693913,
      "index_price": 66489.56956522,
      "mark_index_spread": -0.043616125220284116,
      "timestamp": 1770825315,
      "source": "binance"
    }
  },
  "ETH": {
    "price": {
      "ticker": "ETH",
      "price_usd": 1930.18,
      "price_change_24h": -4.664,
      "price_change_1h": 0.0,
      "price_change_7d": 0.0,
      "high_24h": 2046.1,
      "low_24h": 1901.22,
      "volume_24h": 12365713724.94,
      "volume_change_24h": 0.0,
      "market_cap": 232477588375.0,
      "market_cap_rank": 2,
      "circulating_supply": 120692569.8584684,
      "total_supply": 120692569.8584684,
      "ath": 4946.05,
      "ath_change_percentage": -60.99064,
      "timestamp": 1770825312,
      "source": "binance+coingecko"
    },
    "timestamp": 1770825312,
    "derivatives": {
      "ticker": "ETH",
      "funding_rate": -0.00012343,
      "funding_rate_24h_ago": -0.00012968,
      "funding_rate_change_24h": 6.249999999999989e-06,
      "next_funding_time": 1770825600,
      "open_interest_usd": 3442949938.52072,
      "open_interest_base": 1784660.888,
      "open_interest_change_24h": 0.0,
      "liquidations_24h_long": 0,
      "liquidations_24h_short": 0,
      "liquidations_24h_total": 0,
      "long_short_ratio": 2.4095,
      "mark_price": 1929.19,
      "index_price": 1930.34790698,
      "mark_index_spread": -0.05998436736782515,
      "timestamp": 1770825318,
      "source": "binance"
    }
  },
  "SOL": {
    "price": {
      "ticker": "SOL",
      "price_usd": 79.89,
      "price_change_24h": -5.243,
      "price_change_1h": 0.0,
      "price_change_7d": 0.0,
      "high_24h": 85.1,
      "low_24h": 78.52,
      "volume_24h": 2476768000.9932,
      "volume_change_24h": 0.0,
      "market_cap": 45368408517.0,
      "market_cap_rank": 7,
      "circulating_supply": 567716347.1585077,
      "total_supply": 620121814.7472603,
      "ath": 293.31,
      "ath_change_percentage": -72.76324,
      "timestamp": 1770825312,
      "source": "binance+coingecko"
    },
    "timestamp": 1770825312,
    "derivatives": {
      "ticker": "SOL",
      "funding_rate": -8.483e-05,
      "funding_rate_24h_ago": -9.212e-05,
      "funding_rate_change_24h": 7.2900000000000064e-06,
      "next_funding_time": 1770825600,
      "open_interest_usd": 756280799.6304001,
      "open_interest_base": 9470082.64,
      "open_interest_change_24h": 0.0,
      "liquidations_24h_long": 0,
      "liquidations_24h_short": 0,
      "liquidations_24h_total": 0,
      "long_short_ratio": 2.9277,
      "mark_price": 79.86,
      "index_price": 79.89975743,
      "mark_index_spread": -0.04975913729753929,
      "timestamp": 1770825320,
      "source": "binance"
    }
  },
  "BNB": {
    "price": {
      "ticker": "BNB",
      "price_usd": 592.87,
      "price_change_24h": -4.382,
      "price_change_1h": 0.0,
      "price_change_7d": 0.0,
      "high_24h": 625.33,
      "low_24h": 587.03,
      "volume_24h": 610754410.557,
      "volume_change_24h": 0.0,
      "market_cap": 80708836704.0,
      "market_cap_rank": 5,
      "circulating_supply": 136359470.66,
      "total_supply": 136359470.66,
      "ath": 1369.99,
      "ath_change_percentage": -56.72749,
      "timestamp": 1770825312,
      "source": "binance+coingecko"
    },
    "timestamp": 1770825312,
    "derivatives": {
      "ticker": "BNB",
      "funding_rate": 0.0,
      "funding_rate_24h_ago": 0.0,
      "funding_rate_change_24h": 0.0,
      "next_funding_time": 1770825600,
      "open_interest_usd": 297569834.762,
      "open_interest_base": 502117.4,
      "open_interest_change_24h": 0.0,
      "liquidations_24h_long": 0,
      "liquidations_24h_short": 0,
      "liquidations_24h_total": 0,
      "long_short_ratio": 2.6114,
      "mark_price": 592.63,
      "index_price": 592.78493293,
      "mark_index_spread": -0.026136448717442043,
      "timestamp": 1770825322,
      "source": "binance"
    }
  },
  "DOGE": {
    "price": {
      "ticker": "DOGE",
      "price_usd": 0.08894,
      "price_change_24h": -4.427,
      "price_change_1h": 0.0,
      "price_change_7d": 0.0,
      "high_24h": 0.09412,
      "low_24h": 0.08783,
      "volume_24h": 419258185.35274,
      "volume_change_24h": 0.0,
      "market_cap": 15007609108.0,
      "market_cap_rank": 10,
      "circulating_supply": 168669383126.5791,
      "total_supply": 168697643126.579,
      "ath": 0.731578,
      "ath_change_percentage": -87.83994,
      "timestamp": 1770825312,
      "source": "binance+coingecko"
    },
    "timestamp": 1770825313
  },
  "SHIB": {
    "price": {
      "ticker": "SHIB",
      "price_usd": 5.81e-06,
      "price_change_24h": -3.88338,
      "price_change_1h": -0.8569206166975384,
      "price_change_7d": -13.15309910507612,
      "high_24h": 6.06e-06,
      "low_24h": 5.78e-06,
      "volume_24h": 143172578.0,
      "volume_change_24h": 0.0,
      "market_cap": 3421470615.0,
      "market_cap_rank": 29,
      "circulating_supply": 589243880917864.1,
      "total_supply": 589500418093313.5,
      "ath": 8.616e-05,
      "ath_change_percentage": -93.26034,
      "timestamp": 1770825312,
      "source": "coingecko"
    },
    "timestamp": 1770825313
  },
  "PEPE": {
    "price": {
      "ticker": "PEPE",
      "price_usd": 3.5e-06,
      "price_change_24h": -3.84706,
      "price_change_1h": -2.1285721239651543,
      "price_change_7d": -14.303407852840385,
      "high_24h": 3.7e-06,
      "low_24h": 3.49e-06,
      "volume_24h": 301194666.0,
      "volume_change_24h": 0.0,
      "market_cap": 1473383163.0,
      "market_cap_rank": 52,
      "circulating_supply": 420690000000000.0,
      "total_supply": 420690000000000.0,
      "ath": 2.803e-05,
      "ath_change_percentage": -87.51233,
      "timestamp": 1770825312,
      "source": "coingecko"
    },
    "timestamp": 1770825313
  },
  "FLOKI": {
    "price": {
      "ticker": "FLOKI",
      "price_usd": 2.854e-05,
      "price_change_24h": -4.45161,
      "price_change_1h": -1.2726981415948713,
      "price_change_7d": -15.923571334651026,
      "high_24h": 3.013e-05,
      "low_24h": 2.844e-05,
      "volume_24h": 28808192.0,
      "volume_change_24h": 0.0,
      "market_cap": 275771623.0,
      "market_cap_rank": 138,
      "circulating_supply": 9655017300149.0,
      "total_supply": 10000000000000.0,
      "ath": 0.00034495,
      "ath_change_percentage": -91.73555,
      "timestamp": 1770825312,
      "source": "coingecko"
    },
    "timestamp": 1770825313
  },
  "XMR": {
    "price": {
      "ticker": "XMR",
      "price_usd": 336.04,
      "price_change_24h": 2.239,
      "price_change_1h": 0.0,
      "price_change_7d": 0.0,
      "high_24h": 362.93,
      "low_24h": 319.51,
      "volume_24h": 67274077.84,
      "volume_change_24h": 0.0,
      "market_cap": 6159438470.0,
      "market_cap_rank": 19,
      "circulating_supply": 18446744.07370955,
      "total_supply": 18446744.07370955,
      "ath": 797.73,
      "ath_change_percentage": -58.0286,
      "timestamp": 1770825312,
      "source": "binance+coingecko"
    },
    "timestamp": 1770825313
  },
  "ZEC": {
    "price": {
      "ticker": "ZEC",
      "price_usd": 226.19,
      "price_change_24h": -3.338,
      "price_change_1h": 0.0,
      "price_change_7d": 0.0,
      "high_24h": 239.71,
      "low_24h": 220.5,
      "volume_24h": 364976550.45,
      "volume_change_24h": 0.0,
      "market_cap": 3726461375.0,
      "market_cap_rank": 27,
      "circulating_supply": 16511426.7280448,
      "total_supply": 16511426.7280448,
      "ath": 3191.93,
      "ath_change_percentage": -92.92501,
      "timestamp": 1770825312,
      "source": "binance+coingecko"
    },
    "timestamp": 1770825313
  },
  "DASH": {
    "price": {
      "ticker": "DASH",
      "price_usd": 33.04,
      "price_change_24h": -5.735,
      "price_change_1h": 0.0,
      "price_change_7d": 0.0,
      "high_24h": 35.9,
      "low_24h": 32.21,
      "volume_24h": 47453915.45,
      "volume_change_24h": 0.0,
      "market_cap": 416434832.0,
      "market_cap_rank": 107,
      "circulating_supply": 12585369.1923203,
      "total_supply": 12585369.1923203,
      "ath": 1493.59,
      "ath_change_percentage": -97.78935,
      "timestamp": 1770825312,
      "source": "binance+coingecko"
    },
    "timestamp": 1770825313
  },
  "SCRT": {
    "price": {
      "ticker": "SCRT",
      "price_usd": 0.091,
      "price_change_24h": -3.294,
      "price_change_1h": 0.0,
      "price_change_7d": 0.0,
      "high_24h": 0.0989,
      "low_24h": 0.0889,
      "volume_24h": 1900685.4953,
      "volume_change_24h": 0.0,
      "market_cap": 0.0,
      "market_cap_rank": 0,
      "circulating_supply": 0.0,
      "total_supply": 0.0,
      "ath": 0.0,
      "ath_change_percentage": 0.0,
      "timestamp": 1770825312,
      "source": "binance_futures"
    },
    "timestamp": 1770825313
  },
  "AAVE": {
    "price": {
      "ticker": "AAVE",
      "price_usd": 105.95,
      "price_change_24h": -3.357,
      "price_change_1h": 0.0,
      "price_change_7d": 0.0,
      "high_24h": 113.9,
      "low_24h": 104.61,
      "volume_24h": 93175059.735,
      "volume_change_24h": 0.0,
      "market_cap": 1609333494.0,
      "market_cap_rank": 45,
      "circulating_supply": 15190340.474011041,
      "total_supply": 16000000.0,
      "ath": 661.69,
      "ath_change_percentage": -84.0016,
      "timestamp": 1770825312,
      "source": "binance+coingecko"
    },
    "timestamp": 1770825313
  },
  "UNI": {
    "price": {
      "ticker": "UNI",
      "price_usd": 3.804,
      "price_change_24h": 12.912,
      "price_change_1h": 0.0,
      "price_change_7d": 0.0,
      "high_24h": 4.59,
      "low_24h": 3.219,
      "volume_24h": 391825716.276,
      "volume_change_24h": 0.0,
      "market_cap": 2428881854.0,
      "market_cap_rank": 37,
      "circulating_supply": 633919278.1680214,
      "total_supply": 898904420.0366304,
      "ath": 44.92,
      "ath_change_percentage": -91.39563,
      "timestamp": 1770825312,
      "source": "binance+coingecko"
    },
    "timestamp": 1770825313
  },
  "CRV": {
    "price": {
      "ticker": "CRV",
      "price_usd": 0.226,
      "price_change_24h": -3.83,
      "price_change_1h": 0.0,
      "price_change_7d": 0.0,
      "high_24h": 0.241,
      "low_24h": 0.224,
      "volume_24h": 45684048.333,
      "volume_change_24h": 0.0,
      "market_cap": 335256400.0,
      "market_cap_rank": 121,
      "circulating_supply": 1475430615.0,
      "total_supply": 2351451815.997484,
      "ath": 15.37,
      "ath_change_percentage": -98.51928,
      "timestamp": 1770825312,
      "source": "binance+coingecko"
    },
    "timestamp": 1770825313
  },
  "LDO": {
    "price": {
      "ticker": "LDO",
      "price_usd": 0.3229,
      "price_change_24h": -5.502,
      "price_change_1h": 0.0,
      "price_change_7d": 0.0,
      "high_24h": 0.3443,
      "low_24h": 0.3193,
      "volume_24h": 15225490.2167,
      "volume_change_24h": 0.0,
      "market_cap": 273881222.0,
      "market_cap_rank": 141,
      "circulating_supply": 848066802.5927889,
      "total_supply": 1000000000.0,
      "ath": 7.3,
      "ath_change_percentage": -95.58004,
      "timestamp": 1770825312,
      "source": "binance+coingecko"
    },
    "timestamp": 1770825314
  },
  "defi_tvl": 95512976676.54648,
  "btc_onchain": {
    "ticker": "BTC",
    "exchange_inflow_24h": 0.0,
    "exchange_outflow_24h": 0.0,
    "exchange_netflow_24h": 0.0,
    "active_addresses_24h": 0,
    "active_addresses_change_7d": 0.0,
    "transaction_count_24h": 445942,
    "whale_count": 0,
    "whale_holdings_change_7d": 0.0,
    "hashrate": 894717067767.7898,
    "difficulty": 125864590119494.0,
    "staked_amount": 0.0,
    "staking_ratio": 0.0,
    "velocity": 0.01177256812179432,
    "total_supply": 446.875,
    "max_supply": 21000000,
    "timestamp": 1770825327,
    "source": "blockchain.info",
    "note": "Free API - limited metrics available"
  }
}