{
  "global": {
    "total_market_cap": 2412094822833.789,
    "total_volume_24h": 91127335501.8206,
    "market_cap_change_24h": -0.584629048267344,
    "btc_dominance": 56.45031014108397,
    "eth_dominance": 9.881653492939945,
    "active_cryptocurrencies": 18897,
    "fear_greed_index": 10,
    "fear_greed_classification": "Extreme Fear",
    "alt_season_index": 45,
    "total_open_interest": 8715114406.63689,
    "total_liquidations_24h": 0.0,
    "btc_price": 68132.18632609,
    "btc_change_24h": 0.0,
    "btc_funding_rate": 1.884e-05,
    "btc_open_interest": 5232964927.157221,
    "eth_price": 1974.64614729,
    "eth_change_24h": 0.0,
    "eth_funding_rate": -3.923e-05,
    "eth_open_interest": 3482149479.479669,
    "timestamp": 1771323058,
    "sources": [
      "coingecko",
      "alternative.me",
      "binance"
    ]
  },
  "BTC": {
    "price": {
      "ticker": "BTC",
      "price_usd": 68121.5,
      "price_change_24h": -1.137,
      "price_change_1h": 0.0,
      "price_change_7d": 0.0,
      "high_24h": 70110.9,
      "low_24h": 67250.0,
      "volume_24h": 10578758276.46,
      "volume_change_24h": 0.0,
      "market_cap": 1361148746499.0,
      "market_cap_rank": 1,
      "circulating_supply": 19990746.0,
      "total_supply": 19990746.0,
      "ath": 126080.0,
      "ath_change_percentage": -45.95903,
      "timestamp": 1771323068,
      "source": "binance+coingecko"
    },
    "timestamp": 1771323068,
    "derivatives": {
      "ticker": "BTC",
      "funding_rate": 1.884e-05,
      "funding_rate_24h_ago": 2.672e-05,
      "funding_rate_change_24h": -7.880000000000002e-06,
      "next_funding_time": 1771344000,
      "open_interest_usd": 5232964927.157221,
      "open_interest_base": 76806.062,
      "open_interest_change_24h": 0.0,
      "liquidations_24h_long": 0,
      "liquidations_24h_short": 0,
      "liquidations_24h_total": 0,
      "long_short_ratio": 1.956,
      "mark_price": 68132.18632609,
      "index_price": 68167.40195652,
      "mark_index_spread": -0.05166051429165893,
      "timestamp": 1771323059,
      "source": "binance"
    }
  },
  "ETH": {
    "price": {
      "ticker": "ETH",
      "price_usd": 1974.53,
      "price_change_24h": -0.588,
      "price_change_1h": 0.0,
      "price_change_7d": 0.0,
      "high_24h": 2023.3,
      "low_24h": 1935.39,
      "volume_24h": 8201675300.25,
      "volume_change_24h": 0.0,
      "market_cap": 238278314363.0,
      "market_cap_rank": 2,
      "circulating_supply": 120692440.4714584,
      "total_supply": 120692440.4714584,
      "ath": 4946.05,
      "ath_change_percentage": -60.07109,
      "timestamp": 1771323068,
      "source": "binance+coingecko"
    },
    "timestamp": 1771323068,
    "derivatives": {
      "ticker": "ETH",
      "funding_rate": -3.923e-05,
      "funding_rate_24h_ago": 8.43e-06,
      "funding_rate_change_24h": -4.766e-05,
      "next_funding_time": 1771344000,
      "open_interest_usd": 3482149479.479669,
      "open_interest_base": 1763429.607,
      "open_interest_change_24h": 0.0,
      "liquidations_24h_long": 0,
      "liquidations_24h_short": 0,
      "liquidations_24h_total": 0,
      "long_short_ratio": 2.5448,
      "mark_price": 1974.64614729,
      "index_price": 1975.81023256,
      "mark_index_spread": -0.058916856022742395,
      "timestamp": 1771323062,
      "source": "binance"
    }
  },
  "SOL": {
    "price": {
      "ticker": "SOL",
      "price_usd": 85.83,
      "price_change_24h": -0.105,
      "price_change_1h": 0.0,
      "price_change_7d": 0.0,
      "high_24h": 87.66,
      "low_24h": 82.51,
      "volume_24h": 2147108605.446,
      "volume_change_24h": 0.0,
      "market_cap": 48771987417.0,
      "market_cap_rank": 7,
      "circulating_supply": 568078476.7790872,
      "total_supply": 620525763.600717,
      "ath": 293.31,
      "ath_change_percentage": -70.73275,
      "timestamp": 1771323068,
      "source": "binance+coingecko"
    },
    "timestamp": 1771323068,
    "derivatives": {
      "ticker": "SOL",
      "funding_rate": -9.97e-05,
      "funding_rate_24h_ago": -5.851e-05,
      "funding_rate_change_24h": -4.119e-05,
      "next_funding_time": 1771344000,
      "open_interest_usd": 808413829.2658699,
      "open_interest_base": 9418974.1,
      "open_interest_change_24h": 0.0,
      "liquidations_24h_long": 0,
      "liquidations_24h_short": 0,
      "liquidations_24h_total": 0,
      "long_short_ratio": 2.5575,
      "mark_price": 85.8282251,
      "index_price": 85.89258567,
      "mark_index_spread": -0.07493146177631557,
      "timestamp": 1771323064,
      "source": "binance"
    }
  },
  "BNB": {
    "price": {
      "ticker": "BNB",
      "price_usd": 620.04,
      "price_change_24h": 0.286,
      "price_change_1h": 0.0,
      "price_change_7d": 0.0,
      "high_24h": 632.0,
      "low_24h": 604.2,
      "volume_24h": 448067895.724,
      "volume_change_24h": 0.0,
      "market_cap": 84443571676.0,
      "market_cap_rank": 5,
      "circulating_supply": 136359212.11,
      "total_supply": 136359212.11,
      "ath": 1369.99,
      "ath_change_percentage": -54.78501,
      "timestamp": 1771323068,
      "source": "binance+coingecko"
    },
    "timestamp": 1771323068,
    "derivatives": {
      "ticker": "BNB",
      "funding_rate": 0.0,
      "funding_rate_24h_ago": 0.0,
      "funding_rate_change_24h": 0.0,
      "next_funding_time": 1771344000,
      "open_interest_usd": 310769194.33199996,
      "open_interest_base": 501208.3,
      "open_interest_change_24h": 0.0,
      "liquidations_24h_long": 0,
      "liquidations_24h_short": 0,
      "liquidations_24h_total": 0,
      "long_short_ratio": 2.4819,
      "mark_price": 620.04,
      "index_price": 619.97443318,
      "mark_index_spread": 0.01057572965769733,
      "timestamp": 1771323067,
      "source": "binance"
    }
  },
  "DOGE": {
    "price": {
      "ticker": "DOGE",
      "price_usd": 0.09936,
      "price_change_24h": -3.299,
      "price_change_1h": 0.0,
      "price_change_7d": 0.0,
      "high_24h": 0.10341,
      "low_24h": 0.09844,
      "volume_24h": 625358708.90264,
      "volume_change_24h": 0.0,
      "market_cap": 16752768084.0,
      "market_cap_rank": 9,
      "circulating_supply": 168752253126.579,
      "total_supply": 168774683126.579,
      "ath": 0.731578,
      "ath_change_percentage": -86.41804,
      "timestamp": 1771323068,
      "source": "binance+coingecko"
    },
    "timestamp": 1771323068
  },
  "SHIB": {
    "price": {
      "ticker": "SHIB",
      "price_usd": 6.5e-06,
      "price_change_24h": -2.07305,
      "price_change_1h": 0.2123729749681307,
      "price_change_7d": 8.710533595135162,
      "high_24h": 6.67e-06,
      "low_24h": 6.45e-06,
      "volume_24h": 154756938.0,
      "volume_change_24h": 0.0,
      "market_cap": 3827170055.0,
      "market_cap_rank": 30,
      "circulating_supply": 589243874380800.2,
      "total_supply": 589500411556249.5,
      "ath": 8.616e-05,
      "ath_change_percentage": -92.45554,
      "timestamp": 1771323068,
      "source": "coingecko"
    },
    "timestamp": 1771323068
  },
  "PEPE": {
    "price": {
      "ticker": "PEPE",
      "price_usd": 4.35e-06,
      "price_change_24h": -3.63393,
      "price_change_1h": 0.35916938616237437,
      "price_change_7d": 18.061525855605293,
      "high_24h": 4.55e-06,
      "low_24h": 4.33e-06,
      "volume_24h": 436212735.0,
      "volume_change_24h": 0.0,
      "market_cap": 1828439562.0,
      "market_cap_rank": 43,
      "circulating_supply": 420690000000000.0,
      "total_supply": 420690000000000.0,
      "ath": 2.803e-05,
      "ath_change_percentage": -84.48285,
      "timestamp": 1771323068,
      "source": "coingecko"
    },
    "timestamp": 1771323068
  },
  "FLOKI": {
    "price": {
      "ticker": "FLOKI",
      "price_usd": 3.187e-05,
      "price_change_24h": -0.96287,
      "price_change_1h": 0.20492213230136105,
      "price_change_7d": 6.542525356321745,
      "high_24h": 3.289e-05,
      "low_24h": 3.145e-05,
      "volume_24h": 28075834.0,
      "volume_change_24h": 0.0,
      "market_cap": 307607951.0,
      "market_cap_rank": 133,
      "circulating_supply": 9654936547021.0,
      "total_supply": 10000000000000.0,
      "ath": 0.00034495,
      "ath_change_percentage": -90.76422,
      "timestamp": 1771323068,
      "source": "coingecko"
    },
    "timestamp": 1771323068
  },
  "XMR": {
    "price": {
      "ticker": "XMR",
      "price_usd": 331.38,
      "price_change_24h": 1.203,
      "price_change_1h": 0.0,
      "price_change_7d": 0.0,
      "high_24h": 344.9,
      "low_24h": 322.96,
      "volume_24h": 38534171.49,
      "volume_change_24h": 0.0,
      "market_cap": 6111112156.0,
      "market_cap_rank": 20,
      "circulating_supply": 18446744.07370955,
      "total_supply": 18446744.07370955,
      "ath": 797.73,
      "ath_change_percentage": -58.48887,
      "timestamp": 1771323068,
      "source": "binance+coingecko"
    },
    "timestamp": 1771323068
  },
  "ZEC": {
    "price": {
      "ticker": "ZEC",
      "price_usd": 286.37,
      "price_change_24h": -1.044,
      "price_change_1h": 0.0,
      "price_change_7d": 0.0,
      "high_24h": 310.93,
      "low_24h": 282.0,
      "volume_24h": 459813970.43,
      "volume_change_24h": 0.0,
      "market_cap": 4722831312.0,
      "market_cap_rank": 23,
      "circulating_supply": 16511426.7280448,
      "total_supply": 16511426.7280448,
      "ath": 3191.93,
      "ath_change_percentage": -91.02906,
      "timestamp": 1771323068,
      "source": "binance+coingecko"
    },
    "timestamp": 1771323068
  },
  "DASH": {
    "price": {
      "ticker": "DASH",
      "price_usd": 37.57,
      "price_change_24h": 0.67,
      "price_change_1h": 0.0,
      "price_change_7d": 0.0,
      "high_24h": 39.23,
      "low_24h": 36.71,
      "volume_24h": 40223563.89,
      "volume_change_24h": 0.0,
      "market_cap": 472450450.0,
      "market_cap_rank": 101,
      "circulating_supply": 12589463.2390746,
      "total_supply": 12589463.2390746,
      "ath": 1493.59,
      "ath_change_percentage": -97.48576,
      "timestamp": 1771323068,
      "source": "binance+coingecko"
    },
    "timestamp": 1771323068
  },
  "SCRT": {
    "price": {
      "ticker": "SCRT",
      "price_usd": 0.0865,
      "price_change_24h": -2.809,
      "price_change_1h": 0.0,
      "price_change_7d": 0.0,
      "high_24h": 0.0903,
      "low_24h": 0.0853,
      "volume_24h": 1061670.1941,
      "volume_change_24h": 0.0,
      "market_cap": 0.0,
      "market_cap_rank": 0,
      "circulating_supply": 0.0,
      "total_supply": 0.0,
      "ath": 0.0,
      "ath_change_percentage": 0.0,
      "timestamp": 1771323068,
      "source": "binance_futures"
    },
    "timestamp": 1771323068
  },
  "AAVE": {
    "price": {
      "ticker": "AAVE",
      "price_usd": 124.6,
      "price_change_24h": -2.19,
      "price_change_1h": 0.0,
      "price_change_7d": 0.0,
      "high_24h": 129.18,
      "low_24h": 123.09,
      "volume_24h": 58854349.252,
      "volume_change_24h": 0.0,
      "market_cap": 1892870038.0,
      "market_cap_rank": 41,
      "circulating_supply": 15191735.977164716,
      "total_supply": 16000000.0,
      "ath": 661.69,
      "ath_change_percentage": -81.16356,
      "timestamp": 1771323068,
      "source": "binance+coingecko"
    },
    "timestamp": 1771323068
  },
  "UNI": {
    "price": {
      "ticker": "UNI",
      "price_usd": 3.542,
      "price_change_24h": 0.255,
      "price_change_1h": 0.0,
      "price_change_7d": 0.0,
      "high_24h": 3.628,
      "low_24h": 3.419,
      "volume_24h": 67208301.039,
      "volume_change_24h": 0.0,
      "market_cap": 2248956137.0,
      "market_cap_rank": 39,
      "circulating_supply": 633798762.0380214,
      "total_supply": 898768420.0366304,
      "ath": 44.92,
      "ath_change_percentage": -92.09309,
      "timestamp": 1771323068,
      "source": "binance+coingecko"
    },
    "timestamp": 1771323068
  },
  "CRV": {
    "price": {
      "ticker": "CRV",
      "price_usd": 0.252,
      "price_change_24h": -1.946,
      "price_change_1h": 0.0,
      "price_change_7d": 0.0,
      "high_24h": 0.26,
      "low_24h": 0.247,
      "volume_24h": 29115406.9,
      "volume_change_24h": 0.0,
      "market_cap": 373702852.0,
      "market_cap_rank": 119,
      "circulating_supply": 1477188731.0,
      "total_supply": 2353275815.313261,
      "ath": 15.37,
      "ath_change_percentage": -98.35378,
      "timestamp": 1771323068,
      "source": "binance+coingecko"
    },
    "timestamp": 1771323068
  },
  "LDO": {
    "price": {
      "ticker": "LDO",
      "price_usd": 0.3391,
      "price_change_24h": -0.819,
      "price_change_1h": 0.0,
      "price_change_7d": 0.0,
      "high_24h": 0.3485,
      "low_24h": 0.3318,
      "volume_24h": 12372030.1858,
      "volume_change_24h": 0.0,
      "market_cap": 287372818.0,
      "market_cap_rank": 144,
      "circulating_supply": 848066802.5927889,
      "total_supply": 1000000000.0,
      "ath": 7.3,
      "ath_change_percentage": -95.36115,
      "timestamp": 1771323068,
      "source": "binance+coingecko"
    },
    "timestamp": 1771323068
  },
  "defi_tvl": 96336411426.43298,
  "btc_onchain": {
    "ticker": "BTC",
    "exchange_inflow_24h": 0.0,
    "exchange_outflow_24h": 0.0,
    "exchange_netflow_24h": 0.0,
    "active_addresses_24h": 0,
    "active_addresses_change_7d": 0.0,
    "transaction_count_24h": 632608,
    "whale_count": 0,
    "whale_holdings_change_7d": 0.0,
    "hashrate": 1107446999964.327,
    "difficulty": 125864590119494.0,
    "staked_amount": 0.0,
    "staking_ratio": 0.0,
    "velocity": 0.007771934040030188,
    "total_supply": 553.125,
    "max_supply": 21000000,
    "timestamp": 1771323069,
    "source": "blockchain.info",
    "note": "Free API - limited metrics available"
  }
}