{
  "global": {
    "total_market_cap": 2420071131706.4893,
    "total_volume_24h": 113444456135.30551,
    "market_cap_change_24h": -2.540819104757294,
    "btc_dominance": 56.662553310016115,
    "eth_dominance": 9.80962187633405,
    "active_cryptocurrencies": 18924,
    "fear_greed_index": 12,
    "fear_greed_classification": "Extreme Fear",
    "alt_season_index": 44,
    "total_open_interest": 8865355554.457241,
    "total_liquidations_24h": 17400543.758398008,
    "btc_price": 68601.5,
    "btc_change_24h": 0.0,
    "btc_funding_rate": -2.188e-05,
    "btc_open_interest": 5312857848.221001,
    "eth_price": 1965.23,
    "eth_change_24h": 0.0,
    "eth_funding_rate": -6.574e-05,
    "eth_open_interest": 3552497706.23624,
    "timestamp": 1771215101,
    "sources": [
      "coingecko",
      "alternative.me",
      "binance"
    ]
  },
  "BTC": {
    "price": {
      "ticker": "BTC",
      "price_usd": 68602.1,
      "price_change_24h": -2.478,
      "price_change_1h": 0.0,
      "price_change_7d": 0.0,
      "high_24h": 70938.5,
      "low_24h": 68029.6,
      "volume_24h": 9779561797.82,
      "volume_change_24h": 0.0,
      "market_cap": 1369078511064.0,
      "market_cap_rank": 1,
      "circulating_supply": 19990075.0,
      "total_supply": 19990075.0,
      "ath": 126080.0,
      "ath_change_percentage": -45.59708,
      "timestamp": 1771215109,
      "source": "binance+coingecko"
    },
    "timestamp": 1771215109,
    "derivatives": {
      "ticker": "BTC",
      "funding_rate": -2.188e-05,
      "funding_rate_24h_ago": 2.659e-05,
      "funding_rate_change_24h": -4.847e-05,
      "next_funding_time": 1771228800,
      "open_interest_usd": 5312857848.221001,
      "open_interest_base": 77445.214,
      "open_interest_change_24h": 0.0,
      "liquidations_24h_long": 5634673.373730001,
      "liquidations_24h_short": 2411294.438740002,
      "liquidations_24h_total": 8045967.812470003,
      "long_short_ratio": 1.8571,
      "mark_price": 68601.5,
      "index_price": 68631.26282609,
      "mark_index_spread": -0.0433662807071071,
      "timestamp": 1771215104,
      "source": "binance"
    }
  },
  "ETH": {
    "price": {
      "ticker": "ETH",
      "price_usd": 1965.23,
      "price_change_24h": -5.236,
      "price_change_1h": 0.0,
      "price_change_7d": 0.0,
      "high_24h": 2102.73,
      "low_24h": 1926.83,
      "volume_24h": 9737131323.6,
      "volume_change_24h": 0.0,
      "market_cap": 237021838404.0,
      "market_cap_rank": 2,
      "circulating_supply": 120692449.4802243,
      "total_supply": 120692449.4802243,
      "ath": 4946.05,
      "ath_change_percentage": -60.2686,
      "timestamp": 1771215109,
      "source": "binance+coingecko"
    },
    "timestamp": 1771215109,
    "derivatives": {
      "ticker": "ETH",
      "funding_rate": -6.574e-05,
      "funding_rate_24h_ago": -5.314e-05,
      "funding_rate_change_24h": -1.2600000000000001e-05,
      "next_funding_time": 1771228800,
      "open_interest_usd": 3552497706.23624,
      "open_interest_base": 1807675.288,
      "open_interest_change_24h": 0.0,
      "liquidations_24h_long": 4628830.822190004,
      "liquidations_24h_short": 2400488.4119300013,
      "liquidations_24h_total": 7029319.234120006,
      "long_short_ratio": 2.7651,
      "mark_price": 1965.23,
      "index_price": 1966.22186047,
      "mark_index_spread": -0.050444992497581165,
      "timestamp": 1771215106,
      "source": "binance"
    }
  },
  "SOL": {
    "price": {
      "ticker": "SOL",
      "price_usd": 85.35,
      "price_change_24h": -4.22,
      "price_change_1h": 0.0,
      "price_change_7d": 0.0,
      "high_24h": 91.19,
      "low_24h": 84.71,
      "volume_24h": 2427309970.7134,
      "volume_change_24h": 0.0,
      "market_cap": 48418138640.0,
      "market_cap_rank": 7,
      "circulating_supply": 568079589.0050863,
      "total_supply": 620526707.4976519,
      "ath": 293.31,
      "ath_change_percentage": -70.92301,
      "timestamp": 1771215109,
      "source": "binance+coingecko"
    },
    "timestamp": 1771215109,
    "derivatives": {
      "ticker": "SOL",
      "funding_rate": -8.64e-06,
      "funding_rate_24h_ago": -4.817e-05,
      "funding_rate_change_24h": 3.953e-05,
      "next_funding_time": 1771228800,
      "open_interest_usd": 806823648.5468,
      "open_interest_base": 9454226.02,
      "open_interest_change_24h": 0.0,
      "liquidations_24h_long": 1415950.7442059997,
      "liquidations_24h_short": 358605.38430199976,
      "liquidations_24h_total": 1774556.1285079995,
      "long_short_ratio": 2.4614,
      "mark_price": 85.34,
      "index_price": 85.38261382,
      "mark_index_spread": -0.04990924743746582,
      "timestamp": 1771215107,
      "source": "binance"
    }
  },
  "BNB": {
    "price": {
      "ticker": "BNB",
      "price_usd": 615.43,
      "price_change_24h": -3.529,
      "price_change_1h": 0.0,
      "price_change_7d": 0.0,
      "high_24h": 642.7,
      "low_24h": 608.77,
      "volume_24h": 417121624.103,
      "volume_change_24h": 0.0,
      "market_cap": 83814885096.0,
      "market_cap_rank": 5,
      "circulating_supply": 136359270.14,
      "total_supply": 136359270.14,
      "ath": 1369.99,
      "ath_change_percentage": -55.09842,
      "timestamp": 1771215109,
      "source": "binance+coingecko"
    },
    "timestamp": 1771215109,
    "derivatives": {
      "ticker": "BNB",
      "funding_rate": 0.0,
      "funding_rate_24h_ago": 0.0,
      "funding_rate_change_24h": 0.0,
      "next_funding_time": 1771228800,
      "open_interest_usd": 316110933.6317146,
      "open_interest_base": 513627.04,
      "open_interest_change_24h": 0.0,
      "liquidations_24h_long": 535390.8343000002,
      "liquidations_24h_short": 15309.749,
      "liquidations_24h_total": 550700.5833000002,
      "long_short_ratio": 2.5663,
      "mark_price": 615.44838767,
      "index_price": 615.57695214,
      "mark_index_spread": -0.02088519876403292,
      "timestamp": 1771215108,
      "source": "binance"
    }
  },
  "DOGE": {
    "price": {
      "ticker": "DOGE",
      "price_usd": 0.10263,
      "price_change_24h": -12.019,
      "price_change_1h": 0.0,
      "price_change_7d": 0.0,
      "high_24h": 0.11759,
      "low_24h": 0.10147,
      "volume_24h": 1090523221.67311,
      "volume_change_24h": 0.0,
      "market_cap": 17271518579.0,
      "market_cap_rank": 9,
      "circulating_supply": 168752253126.579,
      "total_supply": 168758863126.579,
      "ath": 0.731578,
      "ath_change_percentage": -85.9748,
      "timestamp": 1771215109,
      "source": "binance+coingecko"
    },
    "timestamp": 1771215109
  },
  "SHIB": {
    "price": {
      "ticker": "SHIB",
      "price_usd": 6.6e-06,
      "price_change_24h": -6.29365,
      "price_change_1h": 0.6696886022585449,
      "price_change_7d": 7.552292567257426,
      "high_24h": 7.11e-06,
      "low_24h": 6.44e-06,
      "volume_24h": 191113850.0,
      "volume_change_24h": 0.0,
      "market_cap": 3888331543.0,
      "market_cap_rank": 29,
      "circulating_supply": 589243877392245.9,
      "total_supply": 589500414567695.1,
      "ath": 8.616e-05,
      "ath_change_percentage": -92.33839,
      "timestamp": 1771215109,
      "source": "coingecko"
    },
    "timestamp": 1771215109
  },
  "PEPE": {
    "price": {
      "ticker": "PEPE",
      "price_usd": 4.46e-06,
      "price_change_24h": -10.98158,
      "price_change_1h": 0.5503537137265359,
      "price_change_7d": 16.91742425803886,
      "high_24h": 5.01e-06,
      "low_24h": 4.35e-06,
      "volume_24h": 788234110.0,
      "volume_change_24h": 0.0,
      "market_cap": 1875009580.0,
      "market_cap_rank": 42,
      "circulating_supply": 420690000000000.0,
      "total_supply": 420690000000000.0,
      "ath": 2.803e-05,
      "ath_change_percentage": -84.09701,
      "timestamp": 1771215109,
      "source": "coingecko"
    },
    "timestamp": 1771215109
  },
  "FLOKI": {
    "price": {
      "ticker": "FLOKI",
      "price_usd": 3.188e-05,
      "price_change_24h": -8.5414,
      "price_change_1h": 0.5077902655915187,
      "price_change_7d": 2.779695786518977,
      "high_24h": 3.515e-05,
      "low_24h": 3.132e-05,
      "volume_24h": 40356478.0,
      "volume_change_24h": 0.0,
      "market_cap": 307483649.0,
      "market_cap_rank": 134,
      "circulating_supply": 9654936547021.0,
      "total_supply": 10000000000000.0,
      "ath": 0.00034495,
      "ath_change_percentage": -90.78423,
      "timestamp": 1771215109,
      "source": "coingecko"
    },
    "timestamp": 1771215109
  },
  "XMR": {
    "price": {
      "ticker": "XMR",
      "price_usd": 323.92,
      "price_change_24h": -6.619,
      "price_change_1h": 0.0,
      "price_change_7d": 0.0,
      "high_24h": 356.32,
      "low_24h": 317.41,
      "volume_24h": 38773887.25,
      "volume_change_24h": 0.0,
      "market_cap": 5969556630.0,
      "market_cap_rank": 20,
      "circulating_supply": 18446744.07370955,
      "total_supply": 18446744.07370955,
      "ath": 797.73,
      "ath_change_percentage": -59.4279,
      "timestamp": 1771215109,
      "source": "binance+coingecko"
    },
    "timestamp": 1771215109
  },
  "ZEC": {
    "price": {
      "ticker": "ZEC",
      "price_usd": 293.37,
      "price_change_24h": -11.17,
      "price_change_1h": 0.0,
      "price_change_7d": 0.0,
      "high_24h": 330.3,
      "low_24h": 287.19,
      "volume_24h": 660785554.08,
      "volume_change_24h": 0.0,
      "market_cap": 4834705638.0,
      "market_cap_rank": 23,
      "circulating_supply": 16511426.7280448,
      "total_supply": 16511426.7280448,
      "ath": 3191.93,
      "ath_change_percentage": -90.80752,
      "timestamp": 1771215109,
      "source": "binance+coingecko"
    },
    "timestamp": 1771215109
  },
  "DASH": {
    "price": {
      "ticker": "DASH",
      "price_usd": 37.62,
      "price_change_24h": -7.111,
      "price_change_1h": 0.0,
      "price_change_7d": 0.0,
      "high_24h": 41.38,
      "low_24h": 36.68,
      "volume_24h": 63721944.03,
      "volume_change_24h": 0.0,
      "market_cap": 473321712.0,
      "market_cap_rank": 104,
      "circulating_supply": 12586777.39486718,
      "total_supply": 12588542.69521533,
      "ath": 1493.59,
      "ath_change_percentage": -97.48752,
      "timestamp": 1771215109,
      "source": "binance+coingecko"
    },
    "timestamp": 1771215109
  },
  "SCRT": {
    "price": {
      "ticker": "SCRT",
      "price_usd": 0.0898,
      "price_change_24h": -4.974,
      "price_change_1h": 0.0,
      "price_change_7d": 0.0,
      "high_24h": 0.0956,
      "low_24h": 0.0875,
      "volume_24h": 1018539.6106,
      "volume_change_24h": 0.0,
      "market_cap": 0.0,
      "market_cap_rank": 0,
      "circulating_supply": 0.0,
      "total_supply": 0.0,
      "ath": 0.0,
      "ath_change_percentage": 0.0,
      "timestamp": 1771215109,
      "source": "binance_futures"
    },
    "timestamp": 1771215109
  },
  "AAVE": {
    "price": {
      "ticker": "AAVE",
      "price_usd": 126.94,
      "price_change_24h": -1.977,
      "price_change_1h": 0.0,
      "price_change_7d": 0.0,
      "high_24h": 131.88,
      "low_24h": 122.48,
      "volume_24h": 71503235.428,
      "volume_change_24h": 0.0,
      "market_cap": 1926684268.0,
      "market_cap_rank": 41,
      "circulating_supply": 15191416.000537667,
      "total_supply": 16000000.0,
      "ath": 661.69,
      "ath_change_percentage": -80.91639,
      "timestamp": 1771215109,
      "source": "binance+coingecko"
    },
    "timestamp": 1771215109
  },
  "UNI": {
    "price": {
      "ticker": "UNI",
      "price_usd": 3.545,
      "price_change_24h": -2.903,
      "price_change_1h": 0.0,
      "price_change_7d": 0.0,
      "high_24h": 3.672,
      "low_24h": 3.389,
      "volume_24h": 88309343.48,
      "volume_change_24h": 0.0,
      "market_cap": 2244727499.0,
      "market_cap_rank": 39,
      "circulating_supply": 633822762.0380214,
      "total_supply": 898792420.0366304,
      "ath": 44.92,
      "ath_change_percentage": -92.16913,
      "timestamp": 1771215109,
      "source": "binance+coingecko"
    },
    "timestamp": 1771215109
  },
  "CRV": {
    "price": {
      "ticker": "CRV",
      "price_usd": 0.254,
      "price_change_24h": -5.576,
      "price_change_1h": 0.0,
      "price_change_7d": 0.0,
      "high_24h": 0.271,
      "low_24h": 0.245,
      "volume_24h": 31765555.443,
      "volume_change_24h": 0.0,
      "market_cap": 375110714.0,
      "market_cap_rank": 120,
      "circulating_supply": 1476820578.0,
      "total_supply": 2352874012.687947,
      "ath": 15.37,
      "ath_change_percentage": -98.35319,
      "timestamp": 1771215109,
      "source": "binance+coingecko"
    },
    "timestamp": 1771215109
  },
  "LDO": {
    "price": {
      "ticker": "LDO",
      "price_usd": 0.3397,
      "price_change_24h": -5.56,
      "price_change_1h": 0.0,
      "price_change_7d": 0.0,
      "high_24h": 0.3618,
      "low_24h": 0.3327,
      "volume_24h": 12582232.3671,
      "volume_change_24h": 0.0,
      "market_cap": 288161040.0,
      "market_cap_rank": 144,
      "circulating_supply": 848066802.5927889,
      "total_supply": 1000000000.0,
      "ath": 7.3,
      "ath_change_percentage": -95.3626,
      "timestamp": 1771215109,
      "source": "binance+coingecko"
    },
    "timestamp": 1771215109
  },
  "defi_tvl": 95747812955.22702,
  "btc_onchain": {
    "ticker": "BTC",
    "exchange_inflow_24h": 0.0,
    "exchange_outflow_24h": 0.0,
    "exchange_netflow_24h": 0.0,
    "active_addresses_24h": 0,
    "active_addresses_change_7d": 0.0,
    "transaction_count_24h": 624331,
    "whale_count": 0,
    "whale_holdings_change_7d": 0.0,
    "hashrate": 1132474050810.9785,
    "difficulty": 125864590119494.0,
    "staked_amount": 0.0,
    "staking_ratio": 0.0,
    "velocity": 0.007143495670886924,
    "total_supply": 565.625,
    "max_supply": 21000000,
    "timestamp": 1771215112,
    "source": "blockchain.info",
    "note": "Free API - limited metrics available"
  }
}