{
  "global": {
    "total_market_cap": 2413117881016.0317,
    "total_volume_24h": 118678699298.56595,
    "market_cap_change_24h": -2.500019045966859,
    "btc_dominance": 56.663202473333754,
    "eth_dominance": 9.790979432354153,
    "active_cryptocurrencies": 18924,
    "fear_greed_index": 12,
    "fear_greed_classification": "Extreme Fear",
    "alt_season_index": 44,
    "total_open_interest": 8818423624.707409,
    "total_liquidations_24h": 16999318.088998005,
    "btc_price": 68369.52050225,
    "btc_change_24h": 0.0,
    "btc_funding_rate": -2.511e-05,
    "btc_open_interest": 5294781934.707089,
    "eth_price": 1956.92,
    "eth_change_24h": 0.0,
    "eth_funding_rate": -7.387e-05,
    "eth_open_interest": 3523641690.00032,
    "timestamp": 1771211638,
    "sources": [
      "coingecko",
      "alternative.me",
      "binance"
    ]
  },
  "BTC": {
    "price": {
      "ticker": "BTC",
      "price_usd": 68366.0,
      "price_change_24h": -1.617,
      "price_change_1h": 0.0,
      "price_change_7d": 0.0,
      "high_24h": 70938.5,
      "low_24h": 68029.6,
      "volume_24h": 10479165530.94,
      "volume_change_24h": 0.0,
      "market_cap": 1366593161002.0,
      "market_cap_rank": 1,
      "circulating_supply": 19990059.0,
      "total_supply": 19990059.0,
      "ath": 126080.0,
      "ath_change_percentage": -45.75356,
      "timestamp": 1771211647,
      "source": "binance+coingecko"
    },
    "timestamp": 1771211648,
    "derivatives": {
      "ticker": "BTC",
      "funding_rate": -2.511e-05,
      "funding_rate_24h_ago": 2.659e-05,
      "funding_rate_change_24h": -5.1699999999999996e-05,
      "next_funding_time": 1771228800,
      "open_interest_usd": 5294781934.707089,
      "open_interest_base": 77443.602,
      "open_interest_change_24h": 0.0,
      "liquidations_24h_long": 5455620.459129998,
      "liquidations_24h_short": 2348798.1002400015,
      "liquidations_24h_total": 7804418.55937,
      "long_short_ratio": 1.8433,
      "mark_price": 68369.52050225,
      "index_price": 68408.68347826,
      "mark_index_spread": -0.05724854509508269,
      "timestamp": 1771211642,
      "source": "binance"
    }
  },
  "ETH": {
    "price": {
      "ticker": "ETH",
      "price_usd": 1956.92,
      "price_change_24h": -4.932,
      "price_change_1h": 0.0,
      "price_change_7d": 0.0,
      "high_24h": 2102.73,
      "low_24h": 1926.83,
      "volume_24h": 10288587891.3,
      "volume_change_24h": 0.0,
      "market_cap": 236145124847.0,
      "market_cap_rank": 2,
      "circulating_supply": 120692449.4802243,
      "total_supply": 120692449.4802243,
      "ath": 4946.05,
      "ath_change_percentage": -60.41198,
      "timestamp": 1771211647,
      "source": "binance+coingecko"
    },
    "timestamp": 1771211648,
    "derivatives": {
      "ticker": "ETH",
      "funding_rate": -7.387e-05,
      "funding_rate_24h_ago": -5.314e-05,
      "funding_rate_change_24h": -2.0729999999999993e-05,
      "next_funding_time": 1771228800,
      "open_interest_usd": 3523641690.00032,
      "open_interest_base": 1800605.896,
      "open_interest_change_24h": 0.0,
      "liquidations_24h_long": 4605958.447940003,
      "liquidations_24h_short": 2369069.8644400006,
      "liquidations_24h_total": 6975028.312380004,
      "long_short_ratio": 2.7566,
      "mark_price": 1956.92,
      "index_price": 1958.21232558,
      "mark_index_spread": -0.06599517136718691,
      "timestamp": 1771211644,
      "source": "binance"
    }
  },
  "SOL": {
    "price": {
      "ticker": "SOL",
      "price_usd": 85.39,
      "price_change_24h": -3.032,
      "price_change_1h": 0.0,
      "price_change_7d": 0.0,
      "high_24h": 91.19,
      "low_24h": 84.83,
      "volume_24h": 2485662238.9094,
      "volume_change_24h": 0.0,
      "market_cap": 48506590404.0,
      "market_cap_rank": 7,
      "circulating_supply": 568079629.0765069,
      "total_supply": 620526737.1891645,
      "ath": 293.31,
      "ath_change_percentage": -70.87837,
      "timestamp": 1771211647,
      "source": "binance+coingecko"
    },
    "timestamp": 1771211648,
    "derivatives": {
      "ticker": "SOL",
      "funding_rate": -2.876e-05,
      "funding_rate_24h_ago": -4.817e-05,
      "funding_rate_change_24h": 1.9410000000000002e-05,
      "next_funding_time": 1771228800,
      "open_interest_usd": 800913341.2174001,
      "open_interest_base": 9379474.66,
      "open_interest_change_24h": 0.0,
      "liquidations_24h_long": 1374886.3781059997,
      "liquidations_24h_short": 358156.18600199977,
      "liquidations_24h_total": 1733042.5641079994,
      "long_short_ratio": 2.4662,
      "mark_price": 85.39,
      "index_price": 85.4462185,
      "mark_index_spread": -0.06579401755503077,
      "timestamp": 1771211645,
      "source": "binance"
    }
  },
  "BNB": {
    "price": {
      "ticker": "BNB",
      "price_usd": 612.82,
      "price_change_24h": -2.826,
      "price_change_1h": 0.0,
      "price_change_7d": 0.0,
      "high_24h": 642.7,
      "low_24h": 608.77,
      "volume_24h": 434775495.465,
      "volume_change_24h": 0.0,
      "market_cap": 83552303493.0,
      "market_cap_rank": 5,
      "circulating_supply": 136359271.5,
      "total_supply": 136359271.5,
      "ath": 1369.99,
      "ath_change_percentage": -55.25804,
      "timestamp": 1771211647,
      "source": "binance+coingecko"
    },
    "timestamp": 1771211648,
    "derivatives": {
      "ticker": "BNB",
      "funding_rate": 0.0,
      "funding_rate_24h_ago": 0.0,
      "funding_rate_change_24h": 0.0,
      "next_funding_time": 1771228800,
      "open_interest_usd": 314534917.592,
      "open_interest_base": 513233.12,
      "open_interest_change_24h": 0.0,
      "liquidations_24h_long": 471518.9041400002,
      "liquidations_24h_short": 15309.749,
      "liquidations_24h_total": 486828.6531400002,
      "long_short_ratio": 2.5714,
      "mark_price": 612.85,
      "index_price": 613.02714805,
      "mark_index_spread": -0.02889726018880641,
      "timestamp": 1771211646,
      "source": "binance"
    }
  },
  "DOGE": {
    "price": {
      "ticker": "DOGE",
      "price_usd": 0.10208,
      "price_change_24h": -10.322,
      "price_change_1h": 0.0,
      "price_change_7d": 0.0,
      "high_24h": 0.11759,
      "low_24h": 0.10147,
      "volume_24h": 1144667204.94981,
      "volume_change_24h": 0.0,
      "market_cap": 17201789063.0,
      "market_cap_rank": 9,
      "circulating_supply": 168752253126.579,
      "total_supply": 168758273126.579,
      "ath": 0.731578,
      "ath_change_percentage": -86.05283,
      "timestamp": 1771211647,
      "source": "binance+coingecko"
    },
    "timestamp": 1771211648
  },
  "SHIB": {
    "price": {
      "ticker": "SHIB",
      "price_usd": 6.56e-06,
      "price_change_24h": -5.23938,
      "price_change_1h": -0.7370716979857057,
      "price_change_7d": 7.438759000415071,
      "high_24h": 7.11e-06,
      "low_24h": 6.44e-06,
      "volume_24h": 194944365.0,
      "volume_change_24h": 0.0,
      "market_cap": 3864013412.0,
      "market_cap_rank": 29,
      "circulating_supply": 589243877392245.9,
      "total_supply": 589500414567695.1,
      "ath": 8.616e-05,
      "ath_change_percentage": -92.38863,
      "timestamp": 1771211648,
      "source": "coingecko"
    },
    "timestamp": 1771211648
  },
  "PEPE": {
    "price": {
      "ticker": "PEPE",
      "price_usd": 4.44e-06,
      "price_change_24h": -9.16479,
      "price_change_1h": -0.8628450357240549,
      "price_change_7d": 17.387086941063107,
      "high_24h": 5.01e-06,
      "low_24h": 4.35e-06,
      "volume_24h": 831412948.0,
      "volume_change_24h": 0.0,
      "market_cap": 1865602479.0,
      "market_cap_rank": 42,
      "circulating_supply": 420690000000000.0,
      "total_supply": 420690000000000.0,
      "ath": 2.803e-05,
      "ath_change_percentage": -84.17508,
      "timestamp": 1771211648,
      "source": "coingecko"
    },
    "timestamp": 1771211648
  },
  "FLOKI": {
    "price": {
      "ticker": "FLOKI",
      "price_usd": 3.173e-05,
      "price_change_24h": -8.47693,
      "price_change_1h": -0.8136613931199927,
      "price_change_7d": 2.8087671070020095,
      "high_24h": 3.515e-05,
      "low_24h": 3.132e-05,
      "volume_24h": 44183567.0,
      "volume_change_24h": 0.0,
      "market_cap": 306208648.0,
      "market_cap_rank": 134,
      "circulating_supply": 9654936547021.0,
      "total_supply": 10000000000000.0,
      "ath": 0.00034495,
      "ath_change_percentage": -90.80369,
      "timestamp": 1771211648,
      "source": "coingecko"
    },
    "timestamp": 1771211648
  },
  "XMR": {
    "price": {
      "ticker": "XMR",
      "price_usd": 320.05,
      "price_change_24h": -9.296,
      "price_change_1h": 0.0,
      "price_change_7d": 0.0,
      "high_24h": 356.32,
      "low_24h": 317.41,
      "volume_24h": 40522369.74,
      "volume_change_24h": 0.0,
      "market_cap": 5896814638.0,
      "market_cap_rank": 20,
      "circulating_supply": 18446744.07370955,
      "total_supply": 18446744.07370955,
      "ath": 797.73,
      "ath_change_percentage": -59.92229,
      "timestamp": 1771211647,
      "source": "binance+coingecko"
    },
    "timestamp": 1771211648
  },
  "ZEC": {
    "price": {
      "ticker": "ZEC",
      "price_usd": 291.18,
      "price_change_24h": -11.228,
      "price_change_1h": 0.0,
      "price_change_7d": 0.0,
      "high_24h": 332.79,
      "low_24h": 287.19,
      "volume_24h": 681993443.87,
      "volume_change_24h": 0.0,
      "market_cap": 4794463917.0,
      "market_cap_rank": 23,
      "circulating_supply": 16511426.7280448,
      "total_supply": 16511426.7280448,
      "ath": 3191.93,
      "ath_change_percentage": -90.88423,
      "timestamp": 1771211647,
      "source": "binance+coingecko"
    },
    "timestamp": 1771211648
  },
  "DASH": {
    "price": {
      "ticker": "DASH",
      "price_usd": 37.31,
      "price_change_24h": -6.911,
      "price_change_1h": 0.0,
      "price_change_7d": 0.0,
      "high_24h": 41.38,
      "low_24h": 36.68,
      "volume_24h": 66448765.57,
      "volume_change_24h": 0.0,
      "market_cap": 468374183.0,
      "market_cap_rank": 103,
      "circulating_supply": 12586777.39486718,
      "total_supply": 12588509.61413456,
      "ath": 1493.59,
      "ath_change_percentage": -97.51054,
      "timestamp": 1771211647,
      "source": "binance+coingecko"
    },
    "timestamp": 1771211648
  },
  "SCRT": {
    "price": {
      "ticker": "SCRT",
      "price_usd": 0.0898,
      "price_change_24h": -3.957,
      "price_change_1h": 0.0,
      "price_change_7d": 0.0,
      "high_24h": 0.0956,
      "low_24h": 0.0875,
      "volume_24h": 1058448.0737,
      "volume_change_24h": 0.0,
      "market_cap": 0.0,
      "market_cap_rank": 0,
      "circulating_supply": 0.0,
      "total_supply": 0.0,
      "ath": 0.0,
      "ath_change_percentage": 0.0,
      "timestamp": 1771211647,
      "source": "binance_futures"
    },
    "timestamp": 1771211648
  },
  "AAVE": {
    "price": {
      "ticker": "AAVE",
      "price_usd": 125.67,
      "price_change_24h": -2.179,
      "price_change_1h": 0.0,
      "price_change_7d": 0.0,
      "high_24h": 131.88,
      "low_24h": 122.48,
      "volume_24h": 73309321.108,
      "volume_change_24h": 0.0,
      "market_cap": 1908753968.0,
      "market_cap_rank": 41,
      "circulating_supply": 15191416.000537667,
      "total_supply": 16000000.0,
      "ath": 661.69,
      "ath_change_percentage": -81.00872,
      "timestamp": 1771211647,
      "source": "binance+coingecko"
    },
    "timestamp": 1771211648
  },
  "UNI": {
    "price": {
      "ticker": "UNI",
      "price_usd": 3.512,
      "price_change_24h": -2.227,
      "price_change_1h": 0.0,
      "price_change_7d": 0.0,
      "high_24h": 3.672,
      "low_24h": 3.389,
      "volume_24h": 93475004.656,
      "volume_change_24h": 0.0,
      "market_cap": 2231862029.0,
      "market_cap_rank": 39,
      "circulating_supply": 633822762.0380214,
      "total_supply": 898792420.0366304,
      "ath": 44.92,
      "ath_change_percentage": -92.16148,
      "timestamp": 1771211647,
      "source": "binance+coingecko"
    },
    "timestamp": 1771211648
  },
  "CRV": {
    "price": {
      "ticker": "CRV",
      "price_usd": 0.251,
      "price_change_24h": -5.993,
      "price_change_1h": 0.0,
      "price_change_7d": 0.0,
      "high_24h": 0.271,
      "low_24h": 0.245,
      "volume_24h": 32471519.574,
      "volume_change_24h": 0.0,
      "market_cap": 369734267.0,
      "market_cap_rank": 120,
      "circulating_supply": 1476815574.0,
      "total_supply": 2352868524.370385,
      "ath": 15.37,
      "ath_change_percentage": -98.37083,
      "timestamp": 1771211647,
      "source": "binance+coingecko"
    },
    "timestamp": 1771211648
  },
  "LDO": {
    "price": {
      "ticker": "LDO",
      "price_usd": 0.3382,
      "price_change_24h": -5.0,
      "price_change_1h": 0.0,
      "price_change_7d": 0.0,
      "high_24h": 0.3618,
      "low_24h": 0.3327,
      "volume_24h": 13184312.7677,
      "volume_change_24h": 0.0,
      "market_cap": 286761527.0,
      "market_cap_rank": 144,
      "circulating_supply": 848066802.5927889,
      "total_supply": 1000000000.0,
      "ath": 7.3,
      "ath_change_percentage": -95.37532,
      "timestamp": 1771211647,
      "source": "binance+coingecko"
    },
    "timestamp": 1771211648
  },
  "defi_tvl": 95932080500.30002,
  "btc_onchain": {
    "ticker": "BTC",
    "exchange_inflow_24h": 0.0,
    "exchange_outflow_24h": 0.0,
    "exchange_netflow_24h": 0.0,
    "active_addresses_24h": 0,
    "active_addresses_change_7d": 0.0,
    "transaction_count_24h": 652116,
    "whale_count": 0,
    "whale_holdings_change_7d": 0.0,
    "hashrate": 1157501101657.63,
    "difficulty": 125864590119494.0,
    "staked_amount": 0.0,
    "staking_ratio": 0.0,
    "velocity": 0.0076411487280010765,
    "total_supply": 578.125,
    "max_supply": 21000000,
    "timestamp": 1771210494,
    "source": "blockchain.info",
    "note": "Free API - limited metrics available"
  }
}